wrapper/__init__.py
wrapper/wrapper.py
bin_wrapper-1.0.5.dist-info/LICENSE
bin_wrapper-1.0.5.dist-info/METADATA
bin_wrapper-1.0.5.dist-info/WHEEL
bin_wrapper-1.0.5.dist-info/top_level.txt
bin_wrapper-1.0.5.dist-info/RECORD
