Metadata-Version: 2.1
Name: bin-wrapper
Version: 1.0.5
Summary: Binary file wrapper
Author-email: myback <54638513+myback@users.noreply.github.com>
License: MIT License
Project-URL: Homepage, https://github.com/myback/bin-wrapper
Project-URL: Bug Tracker, https://github.com/myback/bin-wrapper/issues
Classifier: Programming Language :: Python :: 3.10
Classifier: Programming Language :: Python :: 3.11
Classifier: License :: OSI Approved :: MIT License
Requires-Python: >=3.10
License-File: LICENSE
